Workbook
Name Slicer_Order_Date: #N/A
Name Slicer_Product_ID: #N/A
Name Slicer_Region: #N/A

Sheet dashboard
A1: Total sales | B1: Total orders | C1: AOV | D1: Total discount
A2: =SUM(Orders!L:L) -> -17650856 | B2: =COUNTA(Orders!A:A) -> 1001 | C2: =SUM(Orders!L:L)/COUNTA(Orders!A:A) -> -17633.223 | D2: =SUM(Orders!M:M) -> 174068

Sheet Pivot_Table_Analyze
A1: Row Labels | B1: Sum of Gross Sales
A2: East | B2: 10659
A3: Jan | B3: 770
A4: May | B4: 853
A5: Jun | B5: 6376
A6: 30-Jun | B6: 6376
A7: Sep | B7: 2660
A8: North | B8: 5487
A9: Feb | B9: 714
A10: Mar | B10: 921
A11: Apr | B11: 3852
A12: South | B12: 6418
A13: May | B13: 1843
... A19: Grand Total | B19: 30315

Sheet Orders
A1: Order_ID | B1: Order_Date | C1: Ship_Date | D1: Customer_ID | E1: Product_ID | F1: Quantity | G1: Unit_Price | H1: Discount (%) | I1: Region | J1: Payment_Mode | K1: Gross Sales | L1: Net sales | M1: Cost Price | N1: Total cost | O1: Profit
A2: 100823 | B2: 45657 | C2: 45298 | D2: C1084 | E2: P527 | F2: 4 | G2: 583 | H2: 2 | I2: East | J2: COD | K2: =F2*G2 -> 2332 | L2: =F2*G2*(1-H2) -> -2332 | M2: =_xlfn.XLOOKUP(E2, Products!A:A, Products!E:E) -> 141 | N2: =F2*M2 -> 564 | O2: =L2-N2 -> -2896 | P2: =SUM(O:O) -> -18083605
A3: 100023 | B3: 45655 | C3: 45300 | D3: C1120 | E3: P597 | F3: 4 | G3: 557 | H3: 10 | I3: North | J3: NetBanking | K3: =F3*G3 -> 2228 | L3: =F3*G3*(1-H3) -> -20052 | M3: =_xlfn.XLOOKUP(E3, Products!A:A, Products!E:E) -> 270 | N3: =F3*M3 -> 1080 | O3: =L3-N3 -> -21132
A4: 100526 | B4: 45654 | C4: 45300 | D4: C1051 | E4: P550 | F4: 4 | G4: 1736 | H4: 10 | I4: East | J4: NetBanking | K4: =F4*G4 -> 6944 | L4: =F4*G4*(1-H4) -> -62496 | M4: =_xlfn.XLOOKUP(E4, Products!A:A, Products!E:E) -> 280 | N4: =F4*M4 -> 1120 | O4: =L4-N4 -> -63616
A5: 100207 | B5: 45653 | C5: 45299 | D5: C1169 | E5: P534 | F5: 4 | G5: 943 | H5: 10 | I5: East | J5: NetBanking | K5: =F5*G5 -> 3772 | L5: =F5*G5*(1-H5) -> -33948 | M5: =_xlfn.XLOOKUP(E5, Products!A:A, Products!E:E) -> 181 | N5: =F5*M5 -> 724 | O5: =L5-N5 -> -34672
A6: 100349 | B6: 45652 | C6: 45300 | D6: C1194 | E6: P585 | F6: 4 | G6: 1811 | H6: 15 | I6: South | J6: COD | K6: =F6*G6 -> 7244 | L6: =F6*G6*(1-H6) -> -101416 | M6: =_xlfn.XLOOKUP(E6, Products!A:A, Products!E:E) -> 81 | N6: =F6*M6 -> 324 | O6: =L6-N6 -> -101740
A7: 100600 | B7: 45650 | C7: 45300 | D7: C1241 | E7: P564 | F7: 4 | G7: 1396 | H7: 10 | I7: West | J7: COD | K7: =F7*G7 -> 5584 | L7: =F7*G7*(1-H7) -> -50256 | M7: =_xlfn.XLOOKUP(E7, Products!A:A, Products!E:E) -> 241 | N7: =F7*M7 -> 964 | O7: =L7-N7 -> -51220
A8: 100660 | B8: 45649 | C8: 45294 | D8: C1107 | E8: P594 | F8: 4 | G8: 641 | H8: 15 | I8: North | J8: NetBanking | K8: =F8*G8 -> 2564 | L8: =F8*G8*(1-H8) -> -35896 | M8: =_xlfn.XLOOKUP(E8, Products!A:A, Products!E:E) -> 237 | N8: =F8*M8 -> 948 | O8: =L8-N8 -> -36844
A9: 100611 | B9: 45645 | C9: 45294 | D9: C1293 | E9: P541 | F9: 4 | G9: 430 | H9: 15 | I9: South | J9: NetBanking | K9: =F9*G9 -> 1720 | L9: =F9*G9*(1-H9) -> -24080 | M9: =_xlfn.XLOOKUP(E9, Products!A:A, Products!E:E) -> 93 | N9: =F9*M9 -> 372 | O9: =L9-N9 -> -24452
A10: 100141 | B10: 45644 | C10: 45294 | D10: C1234 | E10: P542 | F10: 4 | G10: 559 | H10: 15 | I10: West | J10: Card | K10: =F10*G10 -> 2236 | L10: =F10*G10*(1-H10) -> -31304 | M10: =_xlfn.XLOOKUP(E10, Products!A:A, Products!E:E) -> 269 | N10: =F10*M10 -> 1076 | O10: =L10-N10 -> -32380
A11: 100437 | B11: 45644 | C11: 45296 | D11: C1191 | E11: P554 | F11: 4 | G11: 1846 | H11: 10 | I11: South | J11: NetBanking | K11: =F11*G11 -> 7384 | L11: =F11*G11*(1-H11) -> -66456 | M11: =_xlfn.XLOOKUP(E11, Products!A:A, Products!E:E) -> 186 | N11: =F11*M11 -> 744 | O11: =L11-N11 -> -67200
A12: 100102 | B12: 45643 | C12: 45297 | D12: C1130 | E12: P556 | F12: 4 | G12: 1449 | H12: 10 | I12: East | J12: UPI | K12: =F12*G12 -> 5796 | L12: =F12*G12*(1-H12) -> -52164 | M12: =_xlfn.XLOOKUP(E12, Products!A:A, Products!E:E) -> 171 | N12: =F12*M12 -> 684 | O12: =L12-N12 -> -52848
A13: 100577 | B13: 45637 | C13: 45297 | D13: C1247 | E13: P584 | F13: 4 | G13: 964 | H13: 10 | I13: North | J13: NetBanking | K13: =F13*G13 -> 3856 | L13: =F13*G13*(1-H13) -> -34704 | M13: =_xlfn.XLOOKUP(E13, Products!A:A, Products!E:E) -> 179 | N13: =F13*M13 -> 716 | O13: =L13-N13 -> -35420
A14: 100136 | B14: 45633 | C14: 45300 | D14: C1009 | E14: P522 | F14: 4 | G14: 1479 | H14: 5 | I14: South | J14: NetBanking | K14: =F14*G14 -> 5916 | L14: =F14*G14*(1-H14) -> -23664 | M14: =_xlfn.XLOOKUP(E14, Products!A:A, Products!E:E) -> 145 | N14: =F14*M14 -> 580 | O14: =L14-N14 -> -24244
... A1001: 100420 | B1001: 45292 | C1001: 45295 | D1001: C1118 | E1001: P590 | F1001: 1 | G1001: 1838 | H1001: 10 | I1001: West | J1001: NetBanking | K1001: =F1001*G1001 -> 1838 | L1001: =F1001*G1001*(1-H1001) -> -16542 | M1001: =_xlfn.XLOOKUP(E1001, Products!A:A, Products!E:E) -> 204 | N1001: =F1001*M1001 -> 204 | O1001: =L1001-N1001 -> -16746

Sheet Products
A1: Product_ID | B1: Product_Name | C1: Category | D1: Subcategory | E1: Cost_Price
A2: P500 | B2: Product_0 | C2: Home | D2: C | E2: 171 | F2: =MID(A2,2,3) -> 500 | G2: =IFERROR(VLOOKUP(A2,Products!A:E,2,FALSE),"Not Found") -> Product_0
A3: P501 | B3: Product_1 | C3: Sports | D3: B | E3: 243 | G3: =ISBLANK(A2) -> FALSE
A4: P502 | B4: Product_2 | C4: Home | D4: A | E4: 126 | G4: =ISNUMBER(A2) -> FALSE
A5: P503 | B5: Product_3 | C5: Electronics | D5: A | E5: 138 | G5: =ISTEXT(A2) -> TRUE
A6: P504 | B6: Product_4 | C6: Sports | D6: C | E6: 113
A7: P505 | B7: Product_5 | C7: Electronics | D7: B | E7: 53
A8: P506 | B8: Product_6 | C8: Beauty | D8: C | E8: 243
A9: P507 | B9: Product_7 | C9: Electronics | D9: C | E9: 242
A10: P508 | B10: Product_8 | C10: Sports | D10: A | E10: 65
A11: P509 | B11: Product_9 | C11: Sports | D11: C | E11: 211
A12: P510 | B12: Product_10 | C12: Sports | D12: C | E12: 82
A13: P511 | B13: Product_11 | C13: Sports | D13: B | E13: 140
A14: P512 | B14: Product_12 | C14: Electronics | D14: C | E14: 184
A15: P513 | B15: Product_13 | C15: Home | D15: B | E15: 179
A16: P514 | B16: Product_14 | C16: Beauty | D16: C | E16: 212
A17: P515 | B17: Product_15 | C17: Beauty | D17: B | E17: 156
... A101: P599 | B101: Product_99 | C101: Fashion | D101: B | E101: 247

Sheet Customers
A1: Customer_ID | B1: Customer_Name | C1: City | D1: State | E1: Join_Date
A2: C1000 | B2: Customer_0 | C2: Chennai | D2: Tamil Nadu | E2: 45079 | G2: =UPPER(Customers!C2) -> CHENNAI | H2: =IF(COUNTA(A2:K2)<COLUMNS(A2:E2),"Missing","Complete") -> 0
A3: C1001 | B3: Customer_1 | C3: Pune | D3: Telangana | E3: 45269 | G3: =UPPER(Customers!C3) -> PUNE
A4: C1002 | B4: Customer_2 | C4: Chennai | D4: Telangana | E4: 45418 | G4: =UPPER(Customers!C4) -> CHENNAI
A5: C1003 | B5: Customer_3 | C5: Chennai | D5: Delhi | E5: 44940 | G5: =UPPER(Customers!C5) -> CHENNAI
A6: C1004 | B6: Customer_4 | C6: Bengaluru | D6: Karnataka | E6: 45351 | G6: =UPPER(Customers!C6) -> BENGALURU
A7: C1005 | B7: Customer_5 | C7: Mumbai | D7: Karnataka | E7: 45034
A8: C1006 | B8: Customer_6 | C8: Delhi | D8: Karnataka | E8: 45337
A9: C1007 | B9: Customer_7 | C9: Bengaluru | D9: Maharashtra | E9: 44964 | G9: =COUNTBLANK(A2:A1000) -> 699
A10: C1008 | B10: Customer_8 | C10: Chennai | D10: Delhi | E10: 45125
A11: C1009 | B11: Customer_9 | C11: Hyderabad | D11: Karnataka | E11: 45489
A12: C1010 | B12: Customer_10 | C12: Chennai | D12: Maharashtra | E12: 44957
A13: C1011 | B13: Customer_11 | C13: Hyderabad | D13: Karnataka | E13: 45284
A14: C1012 | B14: Customer_12 | C14: Bengaluru | D14: Maharashtra | E14: 45276
A15: C1013 | B15: Customer_13 | C15: Delhi | D15: Telangana | E15: 45519
A16: C1014 | B16: Customer_14 | C16: Pune | D16: Karnataka | E16: 45382
A17: C1015 | B17: Customer_15 | C17: Bengaluru | D17: Tamil Nadu | E17: 45401
A18: C1016 | B18: Customer_16 | C18: Mumbai | D18: Delhi | E18: 45341
A19: C1017 | B19: Customer_17 | C19: Hyderabad | D19: Telangana | E19: 45421
A20: C1018 | B20: Customer_18 | C20: Hyderabad | D20: Tamil Nadu | E20: 45544
A21: C1019 | B21: Customer_19 | C21: Pune | D21: Telangana | E21: 45507
... A301: C1299 | B301: Customer_299 | C301: Delhi | D301: Tamil Nadu | E301: 45365

Sheet check
A1: NAME | B1: COUNT | C1: Tax RATE | D1: 5.1
A2: A | B2: 100 | E2: =B2 * $D$1 -> 510
A3: B | B3: 90 | E3: =B3 * $D$1 -> 459
A4: C | B4: 135 | E4: =B4 * $D$1 -> 688.5
A5: D | B5: 31 | E5: =B5 * $D$1 -> 158.1
A7: Jan | B7: 1 | D7: Unit_Price | E7: Discount (%) | F7: multiplicaiton
A8: Feb | B8: 2 | D8: 583 | E8: 5 | F8: =D8*E8 -> 2915
A9: Mar | B9: 3 | D9: 557 | E9: 10 | F9: =D9*E9 -> 5570
A10: Apr | B10: 4 | D10: 1736 | E10: 10 | F10: =D10*E10 -> 17360
A11: May | B11: 5 | D11: 943 | E11: 10 | F11: =D11*E11 -> 9430
A12: Jun | B12: 6 | D12: 1811 | E12: 15 | F12: =D12*E12 -> 27165
A13: Jul | B13: 7 | D13: 1396 | E13: 10 | F13: =D13*E13 -> 13960
A14: Aug | B14: 8 | D14: 641 | E14: 15 | F14: =D14*E14 -> 9615
A15: Sep | B15: 9 | D15: 430 | E15: 15 | F15: =D15*E15 -> 6450
A16: Oct | B16: 10 | D16: 559 | E16: 15 | F16: =D16*E16 -> 8385
A17: Nov | B17: 11 | D17: 1846 | E17: 10 | F17: =D17*E17 -> 18460
A18: Dec | B18: 12 | D18: 1449 | E18: 10 | F18: =D18*E18 -> 14490
D19: 964 | E19: 10 | F19: =D19*E19 -> 9640
D20: 1479 | E20: 5 | F20: =D20*E20 -> 7395
D21: 1675 | E21: 15 | F21: =D21*E21 -> 25125
B24: Customer | C24: 120 | D24: =ISBLANK(A24) -> TRUE | E24: =IFERROR(A24/B24, 0) -> 0
A25: Customer_240 | B25: Customer | C25: 240 | D25: =ISNUMBER(C25) -> TRUE
A26: Customer_360 | B26: Customer | C26: 360
A27: Customer_480 | B27: Customer | C27: 480
A28: Customer_600 | B28: Customer | C28: 600
A29: Customer_720 | B29: Customer | C29: 720
A31: Ashok | B31: =TRIM(A31) -> Ashok | C31: =UPPER(A31) -> ASHOK
A32: ahoks | B32: =CLEAN(A32) -> ahoks | C32: =LOWER(C31) -> ashok
A33: =SUBSTITUTE(A32, "ahoks", "ashok") -> ashok

Sheet check2
A1: 100823 | B1: 45657 | C1: 45298 | D1: C1084
A2: 100023 | B2: 45655 | C2: 45300 | D2: C1120
A3: 100526 | B3: 45654 | C3: 45300 | D3: C1051
A4: 100207 | B4: 45653 | C4: 45299 | D4: C1169
A5: 100349 | B5: 45652 | C5: 45300 | D5: C1194
A6: 100600 | B6: 45650 | C6: 45300 | D6: C1241
A7: 100660 | B7: 45649 | C7: 45294 | D7: C1107
A8: 100611 | B8: 45645 | C8: 45294 | D8: C1293
A9: 100141 | B9: 45644 | C9: 45294 | D9: C1234

Sheet Product_Total Cost
A1: Product_ID | B1: Total cost
A2: P500 | B2: 684
A3: P500 | B3: 684
A4: P500 | B4: 684
A5: P500 | B5: 513
A6: P500 | B6: 342
A7: P500 | B7: 171
A8: P500 | B8: 171
A9: P501 | B9: 972
A10: P501 | B10: 972
A11: P501 | B11: 972
A12: P501 | B12: 729
A13: P501 | B13: 729
... A1001: P599 | B1001: 247
